computations_library-1.1.1.dist-info/top_level.txt
computations_library-1.1.1.dist-info/METADATA
computations_library-1.1.1.dist-info/RECORD
computations_library-1.1.1.dist-info/WHEEL
computations_library/__init__.cpython-36m-x86_64-linux-gnu.so
