Metadata-Version: 2.1
Name: computations-library
Version: 1.1.1
Summary: A classification library used to compute ravi strategy for now
Home-page: UNKNOWN
Author: Mohit Sharma
Author-email: UNKNOWN
License: UNKNOWN
Platform: UNKNOWN
Requires-Dist: numpy (>=1.18.1)
Requires-Dist: Cython (>=0.29.22)
